LICENSE
README.md
setup.cfg
setup.py
src/cronexpr_translator.egg-info/PKG-INFO
src/cronexpr_translator.egg-info/SOURCES.txt
src/cronexpr_translator.egg-info/dependency_links.txt
src/cronexpr_translator.egg-info/requires.txt
src/cronexpr_translator.egg-info/top_level.txt
src/translator/__init__.py
src/translator/constants.py
src/translator/enums.py
src/translator/expression.py
src/translator/translator.py