Metadata-Version: 2.1
Name: cronexpr-translator
Version: 1.1.0
Summary: The python translator for cron expressions
Home-page: https://github.com/poliambro/cronexpr-translator
Author: poliambro
Author-email: poliana.ambrosio.campos@gmail.com
License: MIT
Keywords: cron expression translator
Platform: UNKNOWN
License-File: LICENSE
